{
  "TopicStore": {
    "type": "object",
    "required": ["title"],
    "properties": {
      "title": {
        "type": "string",
        "default": "topic"
      },
      "slug": {
        "type": "string",
        "default": "topic"
      },
      "thumbnail": {
        "type": "string"
      },
      "description": {
        "type": "string"
      },
      "isShowTop": {
        "type": "boolean",
        "default": false
      },
      "status": {
        "type": "number",
        "default": 1
      }
    }
  },
  "TopicUpdate": {
    "type": "object",
    "properties": {
      "title": {
        "type": "string",
        "default": "topic"
      },
      "slug": {
        "type": "string",
        "default": "topic"
      },
      "thumbnail": {
        "type": "string"
      },
      "description": {
        "type": "string"
      },
      "isShowTop": {
        "type": "boolean",
        "default": false
      },
      "status": {
        "type": "number",
        "default": 1
      }
    }
  }
}
